physica/temperature/temperature.py
physica-0.1.0.dist-info/licenses/LICENSE
physica-0.1.0.dist-info/METADATA
physica-0.1.0.dist-info/WHEEL
physica-0.1.0.dist-info/top_level.txt
physica-0.1.0.dist-info/RECORD
