Metadata-Version: 2.4
Name: physica
Version: 0.1.0
Summary: Physics toolkit
Author-email: Anton Sharapov <sharapov.anton@gmail.com>
License: MIT License
Project-URL: Homepage, https://github.com/SharapovAnton/physica
Project-URL: Issues, https://github.com/SharapovAnton/physica/issues
Classifier: Programming Language :: Python :: 3
Classifier: Programming Language :: Python :: 3 :: Only
Classifier: License :: OSI Approved :: MIT License
Classifier: Operating System :: OS Independent
Classifier: Typing :: Typed
Requires-Python: >=3.8
License-File: LICENSE
Provides-Extra: dev
Requires-Dist: pytest; extra == "dev"
Requires-Dist: mypy; extra == "dev"
Requires-Dist: ruff; extra == "dev"
Provides-Extra: qa
Dynamic: license-file
